django_audit_event/__init__.py
django_audit_event/admin.py
django_audit_event/apps.py
django_audit_event/models.py
django_audit_event/tests.py
django_audit_event/urls.py
django_audit_event/views.py
django_audit_event-1.0.4.dist-info/DESCRIPTION.rst
django_audit_event-1.0.4.dist-info/METADATA
django_audit_event-1.0.4.dist-info/RECORD
django_audit_event-1.0.4.dist-info/SOURCES.txt.py
django_audit_event-1.0.4.dist-info/WHEEL
django_audit_event-1.0.4.dist-info/dependency_links.txt.py
django_audit_event-1.0.4.dist-info/metadata.json
django_audit_event-1.0.4.dist-info/top_level.txt
django_audit_event-1.0.4.dist-info/top_level.txt.py
