Metadata-Version: 2.0
Name: django-audit-event
Version: 1.0.4
Summary: Model of event for audit purposes
Home-page: https://bitbucket.org/dleonarski/django-audit-event.git
Author: Dariusz Leonarski
Author-email: dariusz@leonarski.pl
License: MIT
Keywords: django,audit,event
Platform: UNKNOWN
Classifier: Development Status :: 4 - Beta
Classifier: Intended Audience :: Developers
Classifier: Topic :: Software Development :: Build Tools
Classifier: License :: OSI Approved :: MIT License
Classifier: Programming Language :: Python :: 3.4
